qbraid_authentication_server/__init__.py
qbraid_authentication_server/_version.py
qbraid_authentication_server/config.py
qbraid_authentication_server/disk_usage.py
qbraid_authentication_server/handlers.py
qbraid_authentication_server/qiskit_config.py
qbraid_authentication_server/server_ready.py
qbraid_authentication_server/validate_config.py
qbraid_authentication_server/tests/__init__.py
qbraid_authentication_server/tests/test_handlers.py
qbraid_authentication_server-0.1.8.data/data/etc/jupyter/jupyter_server_config.d/qbraid_authentication_server.json
qbraid_authentication_server-0.1.8.data/data/share/jupyter/labextensions/@qbraid/authentication-server/package.json
qbraid_authentication_server-0.1.8.data/data/share/jupyter/labextensions/@qbraid/authentication-server/static/509.2454cfd372b51de74f37.js
qbraid_authentication_server-0.1.8.data/data/share/jupyter/labextensions/@qbraid/authentication-server/static/728.1ee5b36d527b9462ea81.js
qbraid_authentication_server-0.1.8.data/data/share/jupyter/labextensions/@qbraid/authentication-server/static/remoteEntry.302fe106dd4ebeab9c04.js
qbraid_authentication_server-0.1.8.data/data/share/jupyter/labextensions/@qbraid/authentication-server/static/style.js
qbraid_authentication_server-0.1.8.data/data/share/jupyter/labextensions/@qbraid/authentication-server/static/third-party-licenses.json
qbraid_authentication_server-0.1.8.data/data/share/jupyter/labextensions/@qbraid/authentication-server/install.json
qbraid_authentication_server-0.1.8.dist-info/METADATA
qbraid_authentication_server-0.1.8.dist-info/WHEEL
qbraid_authentication_server-0.1.8.dist-info/licenses/LICENSE
qbraid_authentication_server-0.1.8.dist-info/RECORD
